LICENSE.txt
MANIFEST.in
README.txt
requirements.txt
requirements_test.txt
setup.py
pythonsol/AtomicFloat.py
pythonsol/AtomicInt.py
pythonsol/DelayToCount.py
pythonsol/FileUtility.py
pythonsol/HighCache.py
pythonsol/HighCacheEx.py
pythonsol/MemoryCache.py
pythonsol/RedisCache.py
pythonsol/SolBase.py
pythonsol/SysLogger.py
pythonsol/__init__.py
pythonsol.egg-info/PKG-INFO
pythonsol.egg-info/SOURCES.txt
pythonsol.egg-info/dependency_links.txt
pythonsol.egg-info/not-zip-safe
pythonsol.egg-info/requires.txt
pythonsol.egg-info/top_level.txt
pythonsol/daemon/Daemon.py
pythonsol/daemon/__init__.py
pythonsol/meter/MeterBase.py
pythonsol/meter/MeterManager.py
pythonsol/meter/__init__.py
pythonsol/tcpbase/ProtocolParserTextDelimited.py
pythonsol/tcpbase/SignaledBuffer.py
pythonsol/tcpbase/TcpSocketManager.py
pythonsol/tcpbase/__init__.py
pythonsol/tcpclient/TcpClientConfig.py
pythonsol/tcpclient/TcpSimpleClient.py
pythonsol/tcpclient/__init__.py
pythonsol/tcpserver/TcpServer.py
pythonsol/tcpserver/TcpServerConfig.py
pythonsol/tcpserver/TcpServerStat.py
pythonsol/tcpserver/__init__.py
pythonsol/tcpserver/basefactory/TcpServerClientContextAbstractFactory.py
pythonsol/tcpserver/basefactory/__init__.py
pythonsol/tcpserver/clientcontext/TcpServerClientContext.py
pythonsol/tcpserver/clientcontext/TcpServerClientContextFactory.py
pythonsol/tcpserver/clientcontext/__init__.py
pythonsol/tcpserver/queuedclientcontext/TcpServerQueuedClientContext.py
pythonsol/tcpserver/queuedclientcontext/TcpServerQueuedClientContextFactory.py
pythonsol/tcpserver/queuedclientcontext/__init__.py