Metadata-Version: 1.1
Name: pythonsol
Version: 0.0.26
Summary: pythonsol APIs
Home-page: https://knock.center
Author: Laurent Champagnac
Author-email: champagnac.laurent@gmail.com
License:                     GNU GENERAL PUBLIC LICENSE
